fancyimpute/__init__.py
fancyimpute/common.py
fancyimpute/dictionary_helpers.py
fancyimpute/iterative_svd.py
fancyimpute/keras_models.py
fancyimpute/knn.py
fancyimpute/matrix_factorization.py
fancyimpute/nuclear_norm_minimization.py
fancyimpute/scaler.py
fancyimpute/similarity_weighted_averaging.py
fancyimpute/simple_fill.py
fancyimpute/soft_impute.py
fancyimpute/solver.py
fancyimpute-0.6.1.dist-info/LICENSE
fancyimpute-0.6.1.dist-info/METADATA
fancyimpute-0.6.1.dist-info/WHEEL
fancyimpute-0.6.1.dist-info/top_level.txt
fancyimpute-0.6.1.dist-info/RECORD
