Metadata-Version: 2.1
Name: fancyimpute
Version: 0.6.1
Summary: Matrix completion and feature imputation algorithms
Home-page: https://github.com/iskandr/fancyimpute
Author: Alex Rubinsteyn, Sergey Feldman
Author-email: alex.rubinsteyn@gmail.com
License: http://www.apache.org/licenses/LICENSE-2.0.html
Platform: UNKNOWN
Classifier: Development Status :: 4 - Beta
Classifier: Environment :: Console
Classifier: Operating System :: OS Independent
Classifier: Intended Audience :: Science/Research
Classifier: License :: OSI Approved :: Apache Software License
Classifier: Programming Language :: Python
Classifier: Topic :: Scientific/Engineering :: Bio-Informatics
Requires-Dist: knnimpute (>=0.1.0)
Requires-Dist: scikit-learn (>=0.24.2)
Requires-Dist: cvxpy (==1.1.13)
Requires-Dist: cvxopt
Requires-Dist: numpy (==1.19.5)
Requires-Dist: keras (>=2.4.3)
Requires-Dist: tensorflow (>=2.5.1)
